raccoon.py
raccoon_quickstart-0.0.5.dist-info/METADATA
raccoon_quickstart-0.0.5.dist-info/WHEEL
raccoon_quickstart-0.0.5.dist-info/entry_points.txt
raccoon_quickstart-0.0.5.dist-info/top_level.txt
raccoon_quickstart-0.0.5.dist-info/RECORD
