Metadata-Version: 2.1
Name: raccoon-quickstart
Version: 0.0.5
Summary: Raccoon quickstart generator
Home-page: https://github.com/Flying-Raccoon-AI/raccoon-quickstart
Author: Raccoon AI
Author-email: Raccoon AI <team@flyingraccoon.tech>
Project-URL: Homepage, https://github.com/Flying-Raccoon-AI/raccoon-quickstart
Classifier: Programming Language :: Python :: 3.8
Classifier: License :: OSI Approved :: MIT License
Classifier: Operating System :: OS Independent
Requires-Python: >=3.7
Requires-Dist: click
Requires-Dist: pyperclip
Requires-Dist: setuptools
Provides-Extra: test
Requires-Dist: pytest; extra == "test"
Requires-Dist: pytest-cov; extra == "test"
